qmm/__init__.py
qmm/operators.py
qmm/py.typed
qmm/qmm.py
qmm/test_res_val.py
qmm-0.19.0.dist-info/METADATA
qmm-0.19.0.dist-info/WHEEL
qmm-0.19.0.dist-info/licenses/LICENSE
qmm-0.19.0.dist-info/RECORD
