Metadata-Version: 2.4
Name: qmm
Version: 0.19.0
Summary: Quadratic Majorize-Minimize Python toolbox
License: GPL-3.0-or-later
License-File: LICENSE
Keywords: optimization,MM,surogate,criterion,objective,learning
Author: François Orieux
Author-email: francois.orieux@universite-paris-saclay.fr
Maintainer: François Orieux
Maintainer-email: francois.orieux@universite-paris-saclay.fr
Requires-Python: >=3.8,<4.0
Classifier: Development Status :: 4 - Beta
Classifier: Intended Audience :: Developers
Classifier: Intended Audience :: Science/Research
Classifier: License :: OSI Approved :: GNU General Public License v3 or later (GPLv3+)
Classifier: Operating System :: OS Independent
Classifier: Programming Language :: Python :: 3
Classifier: Programming Language :: Python :: 3.8
Classifier: Programming Language :: Python :: 3.9
Classifier: Programming Language :: Python :: 3.10
Classifier: Programming Language :: Python :: 3.11
Classifier: Programming Language :: Python :: 3.12
Classifier: Programming Language :: Python :: 3.13
Classifier: Programming Language :: Python :: 3.14
Classifier: Programming Language :: Python :: Implementation :: CPython
Classifier: Topic :: Scientific/Engineering
Classifier: Topic :: Scientific/Engineering :: Mathematics
Classifier: Typing :: Typed
Requires-Dist: numpy (>=1.19,<3.0)
Project-URL: Author webpage, https://pro.orieux.fr/
Project-URL: Bug Tracker, https://github.com/forieux/qmm/issues
Project-URL: Documentation, https://qmm.readthedocs.io/en/stable/
Project-URL: Homepage, https://qmm.readthedocs.io/en/stable/
Project-URL: Repository, https://github.com/forieux/qmm/
